girth_mcmc/__init__.py
girth_mcmc/girth_class.py
girth_mcmc/dichotomous/__init__.py
girth_mcmc/dichotomous/multidimensional_twopl.py
girth_mcmc/dichotomous/onepl_model.py
girth_mcmc/dichotomous/rasch_model.py
girth_mcmc/dichotomous/threepl_model.py
girth_mcmc/dichotomous/twopl_model.py
girth_mcmc/distributions/__init__.py
girth_mcmc/distributions/partial_credit.py
girth_mcmc/distributions/rayleigh.py
girth_mcmc/polytomous/__init__.py
girth_mcmc/polytomous/graded_response_model.py
girth_mcmc/polytomous/multidimensional_grm.py
girth_mcmc/polytomous/multidimensional_pcm.py
girth_mcmc/polytomous/partial_credit_model.py
girth_mcmc/utils/__init__.py
girth_mcmc/utils/missing_data.py
girth_mcmc/utils/multidimensional_utils.py
girth_mcmc/utils/options.py
girth_mcmc-0.6.0.dist-info/LICENSE.txt
girth_mcmc-0.6.0.dist-info/METADATA
girth_mcmc-0.6.0.dist-info/WHEEL
girth_mcmc-0.6.0.dist-info/top_level.txt
girth_mcmc-0.6.0.dist-info/RECORD
