Metadata-Version: 2.1
Name: girth-mcmc
Version: 0.6.0
Summary: Bayesian Item Response Theory Estimation.
Home-page: https://github.com/eribean/girth_mcmc/
Author: Ryan C. Sanchez
Author-email: rsanchez44@gatech.edu
License: MIT
Keywords: IRT,Psychometrics,Item Response Theory,MCMC,Bayesian
Platform: UNKNOWN
Classifier: Development Status :: 3 - Alpha
Classifier: Intended Audience :: Science/Research
Classifier: Topic :: Scientific/Engineering
Classifier: License :: OSI Approved :: MIT License
Classifier: Programming Language :: Python :: 3.8
Classifier: Programming Language :: Python :: 3.9
License-File: LICENSE.txt
Requires-Dist: numpy
Requires-Dist: scipy
Requires-Dist: pymc3
Requires-Dist: girth
